csvcubedpmd/__init__.py
csvcubedpmd/config/__init__.py
csvcubedpmd/config/pmdconfig.py
csvcubedpmd/csvwcli/__init__.py
csvcubedpmd/csvwcli/findwhere.py
csvcubedpmd/dcatcli/__init__.py
csvcubedpmd/dcatcli/pmdify.py
csvcubedpmd/main.py
csvcubedpmd/models/CsvCubedOutputType.py
csvcubedpmd/models/__init__.py
csvcubedpmd/models/csvwithcolumndefinitions.py
csvcubedpmd/models/rdf/__init__.py
csvcubedpmd/models/rdf/pmdcat.py
csvcubedpmd/urireplacement/__init__.py
csvcubedpmd/urireplacement/urireplacement.py
csvcubedpmd/utils/__init__.py
csvcubedpmd/utils/rdflibutils.py
csvcubedpmd/utils/sparql.py
csvcubed_pmd-1.0.14.dist-info/LICENSE
csvcubed_pmd-1.0.14.dist-info/METADATA
csvcubed_pmd-1.0.14.dist-info/WHEEL
csvcubed_pmd-1.0.14.dist-info/entry_points.txt
csvcubed_pmd-1.0.14.dist-info/RECORD
